{
  "info": {
    "description": "Lableme Dataset",
    "version": 4.6,
    "year": 2022
  },
  "license": [
    "BUAA"
  ],
  "images": [
    {
      "height": 1024,
      "width": 1024,
      "id": 0,
      "file_name": "1106.jpg"
    }
  ],
  "annotations": [
    {
      "id": 0,
      "image_id": 0,
      "iscrowd": 0,
      "area": 1.0,
      "segmentation": [
        [
          4.25,
          2.166666666666667,
          1023.0,
          1019.875
        ]
      ],
      "bbox": [
        [
          4.25,
          2.166666666666667,
          1018.75,
          1017.7083333333334
        ]
      ],
      "keypoints": [
        [
          [
            484.9785407725322,
            580.68669527897,
            1
          ],
          [
            627.4406332453826,
            559.3667546174142,
            1
          ],
          [
            451.45118733509236,
            607.915567282322,
            1
          ],
          [
            511.08179419525067,
            631.6622691292876,
            1
          ],
          [
            476.2532981530343,
            626.3852242744064,
            1
          ]
        ]
      ],
      "num_keypoints": 5
    }
  ],
  "categories": [
    {
      "supercategory": "hand",
      "id": 1,
      "name": "hand",
      "keypoints": [
        "metacarpal-L",
        "metacarpal-R",
        "trapezium",
        "metacarpal-BL",
        "index"
      ]
    }
  ]
}