{
  "info": {
    "description": "Lableme Dataset",
    "version": 4.6,
    "year": 2022
  },
  "license": [
    "BUAA"
  ],
  "images": [
    {
      "height": 1024,
      "width": 1024,
      "id": 0,
      "file_name": "334.jpg"
    }
  ],
  "annotations": [
    {
      "id": 0,
      "image_id": 0,
      "iscrowd": 0,
      "area": 1.0,
      "segmentation": [
        [
          4.25,
          2.166666666666667,
          1023.0,
          1019.875
        ]
      ],
      "bbox": [
        [
          4.25,
          2.166666666666667,
          1018.75,
          1017.7083333333334
        ]
      ],
      "keypoints": [
        [
          [
            604.2918454935622,
            607.725321888412,
            1
          ],
          [
            740.3433476394849,
            525.7510729613733,
            1
          ],
          [
            558.3690987124463,
            650.6437768240343,
            1
          ],
          [
            631.7596566523605,
            667.381974248927,
            1
          ],
          [
            638.62660944206,
            698.2832618025751,
            1
          ]
        ]
      ],
      "num_keypoints": 5
    }
  ],
  "categories": [
    {
      "supercategory": "hand",
      "id": 1,
      "name": "hand",
      "keypoints": [
        "metacarpal-L",
        "metacarpal-R",
        "trapezium",
        "metacarpal-BL",
        "index"
      ]
    }
  ]
}