{
  "info": {
    "description": "Lableme Dataset",
    "version": 4.6,
    "year": 2022
  },
  "license": [
    "BUAA"
  ],
  "images": [
    {
      "height": 1024,
      "width": 1024,
      "id": 0,
      "file_name": "426.jpg"
    }
  ],
  "annotations": [
    {
      "id": 0,
      "image_id": 0,
      "iscrowd": 0,
      "area": 1.0,
      "segmentation": [
        [
          5.197867298578217,
          1.6927330173776154,
          1023.9478672985783,
          1019.401066350711
        ]
      ],
      "bbox": [
        [
          5.197867298578217,
          1.6927330173776154,
          1018.7500000000001,
          1017.7083333333334
        ]
      ],
      "keypoints": [
        [
          [
            309.45833333333337,
            651.125,
            1
          ],
          [
            502.3121387283237,
            531.2138728323699,
            1
          ],
          [
            288.4393063583815,
            711.5606936416185,
            1
          ],
          [
            370.9166666666667,
            718.8333333333334,
            1
          ],
          [
            372.8323699421965,
            756.0693641618498,
            1
          ]
        ]
      ],
      "num_keypoints": 5
    }
  ],
  "categories": [
    {
      "supercategory": "hand",
      "id": 1,
      "name": "hand",
      "keypoints": [
        "metacarpal-L",
        "metacarpal-R",
        "trapezium",
        "metacarpal-BL",
        "index"
      ]
    }
  ]
}