{
  "info": {
    "description": "Lableme Dataset",
    "version": 4.6,
    "year": 2022
  },
  "license": [
    "BUAA"
  ],
  "images": [
    {
      "height": 1024,
      "width": 1024,
      "id": 0,
      "file_name": "531.jpg"
    }
  ],
  "annotations": [
    {
      "id": 0,
      "image_id": 0,
      "iscrowd": 0,
      "area": 1.0,
      "segmentation": [
        [
          4.25,
          2.166666666666667,
          1023.0,
          1019.875
        ]
      ],
      "bbox": [
        [
          4.25,
          2.166666666666667,
          1018.75,
          1017.7083333333334
        ]
      ],
      "keypoints": [
        [
          [
            372.0379146919432,
            666.8246445497631,
            1
          ],
          [
            511.37440758293843,
            586.2559241706161,
            1
          ],
          [
            348.34123222748815,
            727.9620853080569,
            1
          ],
          [
            410.4265402843602,
            733.6492890995261,
            1
          ],
          [
            424.6445497630332,
            781.0426540284361,
            1
          ]
        ]
      ],
      "num_keypoints": 5
    }
  ],
  "categories": [
    {
      "supercategory": "hand",
      "id": 1,
      "name": "hand",
      "keypoints": [
        "metacarpal-L",
        "metacarpal-R",
        "trapezium",
        "metacarpal-BL",
        "index"
      ]
    }
  ]
}