{
  "info": {
    "description": "Lableme Dataset",
    "version": 4.6,
    "year": 2022
  },
  "license": [
    "BUAA"
  ],
  "images": [
    {
      "height": 1024,
      "width": 1024,
      "id": 0,
      "file_name": "896.jpg"
    }
  ],
  "annotations": [
    {
      "id": 0,
      "image_id": 0,
      "iscrowd": 0,
      "area": 1.0,
      "segmentation": [
        [
          4.25,
          2.166666666666667,
          1023.0,
          1019.875
        ]
      ],
      "bbox": [
        [
          4.25,
          2.166666666666667,
          1018.75,
          1017.7083333333334
        ]
      ],
      "keypoints": [
        [
          [
            348.54881266490764,
            424.8021108179419,
            1
          ],
          [
            436.4116094986807,
            482.0580474934037,
            1
          ],
          [
            336.14775725593665,
            383.90501319261216,
            1
          ],
          [
            384.6965699208443,
            375.4617414248021,
            1
          ],
          [
            398.15303430079155,
            345.1187335092348,
            1
          ]
        ]
      ],
      "num_keypoints": 5
    }
  ],
  "categories": [
    {
      "supercategory": "hand",
      "id": 1,
      "name": "hand",
      "keypoints": [
        "metacarpal-L",
        "metacarpal-R",
        "trapezium",
        "metacarpal-BL",
        "index"
      ]
    }
  ]
}