{
  "info": {
    "description": "Lableme Dataset",
    "version": 4.6,
    "year": 2022
  },
  "license": [
    "BUAA"
  ],
  "images": [
    {
      "height": 1024,
      "width": 1024,
      "id": 0,
      "file_name": "938.jpg"
    }
  ],
  "annotations": [
    {
      "id": 0,
      "image_id": 0,
      "iscrowd": 0,
      "area": 1.0,
      "segmentation": [
        [
          4.25,
          2.166666666666667,
          1023.0,
          1019.875
        ]
      ],
      "bbox": [
        [
          4.25,
          2.166666666666667,
          1018.75,
          1017.7083333333334
        ]
      ],
      "keypoints": [
        [
          [
            340.0871459694989,
            518.7363834422658,
            1
          ],
          [
            465.5773420479303,
            555.9912854030501,
            1
          ],
          [
            318.9542483660131,
            490.8496732026144,
            1
          ],
          [
            370.8061002178649,
            471.0239651416122,
            1
          ],
          [
            361.43790849673206,
            477.77777777777777,
            1
          ]
        ]
      ],
      "num_keypoints": 5
    }
  ],
  "categories": [
    {
      "supercategory": "hand",
      "id": 1,
      "name": "hand",
      "keypoints": [
        "metacarpal-L",
        "metacarpal-R",
        "trapezium",
        "metacarpal-BL",
        "index"
      ]
    }
  ]
}